rpg_pybot/__init__.py
rpg_pybot/dice/__init__.py
rpg_pybot/dice/roll.py
rpg_pybot/players/__init__.py
rpg_pybot/players/player.py
rpg_pybot-0.0.1.dist-info/METADATA
rpg_pybot-0.0.1.dist-info/WHEEL
rpg_pybot-0.0.1.dist-info/top_level.txt
rpg_pybot-0.0.1.dist-info/RECORD
