Metadata-Version: 2.1
Name: rpg-pybot
Version: 0.0.1
Summary: A small RPG simulator
Home-page: https://github.com/W1ndeck/RPG-PYBOT
Author: Lucas Mateus da Silva
Author-email: lmateus1067@outlook.com
Requires-Python: >=3.10.5
